setup.cfg
setup.py
langid/__init__.py
langid/langid.py
langid.egg-info/PKG-INFO
langid.egg-info/SOURCES.txt
langid.egg-info/dependency_links.txt
langid.egg-info/entry_points.txt
langid.egg-info/not-zip-safe
langid.egg-info/requires.txt
langid.egg-info/top_level.txt
langid/train/BLweight.py
langid/train/DFfeatureselect.py
langid/train/IGDweight.py
langid/train/IGweight.py
langid/train/LDfeatureselect.py
langid/train/NBtrain.py
langid/train/TOPfs.py
langid/train/__init__.py
langid/train/common.py
langid/train/index.py
langid/train/scanner.py
langid/train/tokenize.py
langid/train/train.py
langid/train/validate.py