Metadata-Version: 1.0
Name: langid
Version: 1.1.4dev
Summary: langid.py is a standalone Language Identification (LangID) tool.
Home-page: https://github.com/saffsd/langid.py
Author: Marco Lui
Author-email: saffsd@gmail.com
License: BSD
Keywords: language detection
Platform: UNKNOWN
